[
	{
		"Identifier": "FL004",
		"FourOperationsType": 2,
		"MaximumLimit": 30,
		"NumberOfQuestions": 1,
		"QuestionType": 3,
		"Signs": [ 0, 1 ],
		"Reserve": "{\"Amount\" : 7}"
	},
	{
		"Identifier": "FL001",
		"FourOperationsType": 1,
		"MaximumLimit": 20,
		"NumberOfQuestions": 1,
		"QuestionType": 1,
		"Signs": [ 1 ],
		"Reserve": "{\"Amount\" : 10}"
	},
	{
		"Identifier": "FL002",
		"FourOperationsType": 1,
		"MaximumLimit": 30,
		"NumberOfQuestions": 1,
		"QuestionType": 3,
		"Signs": [ 0 ],
		"Reserve": "{\"Amount\" : 4}"
	},
	{
		"Identifier": "FL003",
		"FourOperationsType": 1,
		"MaximumLimit": 40,
		"NumberOfQuestions": 1,
		"QuestionType": 3,
		"Signs": [ 1 ],
		"Reserve": "{\"Amount\" : 3}"
	}
]
